von_neumann_transform/__init__.py
von_neumann_transform/basis.py
von_neumann_transform/methods.py
von_neumann_transform/overlap.py
von_neumann_transform/projection.py
von_neumann_transform/reconstruction.py
von_neumann_transform/transform.py
von_neumann_transform-0.1.1.dist-info/METADATA
von_neumann_transform-0.1.1.dist-info/WHEEL
von_neumann_transform-0.1.1.dist-info/licenses/LICENSE
von_neumann_transform-0.1.1.dist-info/RECORD
