Metadata-Version: 2.4
Name: von_neumann_transform
Version: 0.1.1
Summary: A Python package for efficient von Neumann transform
Project-URL: Homepage, https://github.com/xmiaocat/von-neumann-transform
Project-URL: Issues, https://github.com/xmiaocat/von-neumann-transform/issues
Author-email: Xincheng Miao <xincheng.miao@uni-wuerzburg.de>
License-Expression: Apache-2.0
License-File: LICENSE
Keywords: joint time-frequency analysis,ultrashort laser pulse,von Neumann representation,von Neumann transform
Classifier: Development Status :: 4 - Beta
Classifier: License :: OSI Approved :: Apache Software License
Classifier: Operating System :: OS Independent
Classifier: Programming Language :: Python :: 3
Classifier: Programming Language :: Python :: 3.11
Classifier: Programming Language :: Python :: 3.12
Classifier: Programming Language :: Python :: 3.13
Classifier: Programming Language :: Python :: Implementation :: CPython
Classifier: Topic :: Scientific/Engineering
Classifier: Topic :: Scientific/Engineering :: Chemistry
Classifier: Topic :: Scientific/Engineering :: Mathematics
Classifier: Topic :: Scientific/Engineering :: Physics
Classifier: Typing :: Typed
Requires-Python: >=3.11
Requires-Dist: numpy==2.3.*
Requires-Dist: scipy==1.16.*
Provides-Extra: dev
Requires-Dist: black; extra == 'dev'
Requires-Dist: flake8; extra == 'dev'
Requires-Dist: flake8-pyproject; extra == 'dev'
Requires-Dist: mypy; extra == 'dev'
Requires-Dist: pre-commit; extra == 'dev'
Requires-Dist: pytest-cov>=6.2; extra == 'dev'
Requires-Dist: pytest>=8.4; extra == 'dev'
